{
  "name": "DonaTrack",
  "nodes": [
    {
      "parameters": {
        "rule": {
          "interval": [
            {
              "field": "months"
            }
          ]
        }
      },
      "type": "n8n-nodes-base.scheduleTrigger",
      "typeVersion": 1.3,
      "position": [
        -768,
        112
      ],
      "id": "1f8aee98-9d54-4964-b643-cc9e481ab8b4",
      "name": "Schedule Trigger"
    },
    {
      "parameters": {
        "url": "http://host.docker.internal:8082/rankingDonantes",
        "options": {}
      },
      "type": "n8n-nodes-base.httpRequest",
      "typeVersion": 4.4,
      "position": [
        -528,
        112
      ],
      "id": "494775cc-8a4b-4915-9ed2-20c055ba0df2",
      "name": "HTTP Request"
    },
    {
      "parameters": {
        "jsCode": "const items = $input.all();\n\nfor (const [index, item] of items.entries()) {\n  item.json.ranking = [{ posicion: index+1, identificador: item.json.mail.direccion }]\n}\n\nreturn items;"
      },
      "type": "n8n-nodes-base.code",
      "typeVersion": 2,
      "position": [
        -256,
        112
      ],
      "id": "2ae7cfe2-4791-4294-8093-87c756a96495",
      "name": "Code in JavaScript1"
    },
    {
      "parameters": {
        "options": {}
      },
      "type": "n8n-nodes-base.respondToWebhook",
      "typeVersion": 1.5,
      "position": [
        -48,
        -240
      ],
      "id": "c3d0fc71-7cda-44b9-8ee5-6d562c9371e2",
      "name": "Respond to Webhook"
    },
    {
      "parameters": {
        "authentication": "oAuth2",
        "resource": "message",
        "guildId": {
          "__rl": true,
          "value": "1525233519595487315",
          "mode": "id"
        },
        "channelId": {
          "__rl": true,
          "value": "1525233555771232398",
          "mode": "list",
          "cachedResultName": "avisos",
          "cachedResultUrl": "https://discord.com/channels/1525233519595487315/1525233555771232398"
        },
        "content": "=Felicitaciones {{ $json.body.user }}! Sos un {{ $json.body.badge }}. {{ $json.body.description }}\n\n",
        "options": {},
        "files": {
          "values": [
            {}
          ]
        }
      },
      "type": "n8n-nodes-base.discord",
      "typeVersion": 2,
      "position": [
        -320,
        -240
      ],
      "id": "0ef1f4cb-fb28-4642-9f72-3407fe43586a",
      "name": "Send a message",
      "webhookId": "986d6482-edae-4d55-8fa3-420d3b0af2f2",
      "executeOnce": false,
      "retryOnFail": false,
      "credentials": {
        "discordOAuth2Api": {
          "id": "EXBwObtNa7dhjgQM",
          "name": "Discord account"
        }
      }
    },
    {
      "parameters": {
        "url": "https://picsum.photos/800/600",
        "options": {}
      },
      "type": "n8n-nodes-base.httpRequest",
      "typeVersion": 4.4,
      "position": [
        -544,
        -240
      ],
      "id": "c8175ead-dd25-4a23-82e4-be6798d38c70",
      "name": "Imagen"
    },
    {
      "parameters": {
        "httpMethod": "POST",
        "path": "=10973e82-bed5-4563-9f2f-b2b37f836b00",
        "responseMode": "responseNode",
        "options": {}
      },
      "type": "n8n-nodes-base.webhook",
      "typeVersion": 2.1,
      "position": [
        -768,
        -240
      ],
      "id": "523c3439-3be9-493f-9053-693c14b6367d",
      "name": "Discord Webhook",
      "webhookId": "10973e82-bed5-4563-9f2f-b2b37f836b00"
    },
    {
      "parameters": {
        "authentication": "oAuth2",
        "resource": "message",
        "guildId": {
          "__rl": true,
          "value": "1525233519595487315",
          "mode": "id"
        },
        "channelId": {
          "__rl": true,
          "value": "1525623809091174512",
          "mode": "list",
          "cachedResultName": "rankings",
          "cachedResultUrl": "https://discord.com/channels/1525233519595487315/1525623809091174512"
        },
        "content": "=Ranking del mes {{ new Date().toLocaleString('es-AR', { month: 'long', year: 'numeric' }) }}:\n\n{{\n$input.all()\n  .map(item => {\n    const r = item.json.ranking[0];\n    return `${r.posicion}. ${r.identificador}`;\n  })\n  .join('\\n')\n}}",
        "options": {}
      },
      "type": "n8n-nodes-base.discord",
      "typeVersion": 2,
      "position": [
        16,
        112
      ],
      "id": "4c361def-de12-4846-9b8e-8814b54fd1c8",
      "name": "Send a message1",
      "webhookId": "986d6482-edae-4d55-8fa3-420d3b0af2f2",
      "executeOnce": false,
      "retryOnFail": false,
      "credentials": {
        "discordOAuth2Api": {
          "id": "EXBwObtNa7dhjgQM",
          "name": "Discord account"
        }
      }
    }
  ],
  "pinData": {},
  "connections": {
    "Schedule Trigger": {
      "main": [
        [
          {
            "node": "HTTP Request",
            "type": "main",
            "index": 0
          }
        ]
      ]
    },
    "HTTP Request": {
      "main": [
        [
          {
            "node": "Code in JavaScript1",
            "type": "main",
            "index": 0
          }
        ]
      ]
    },
    "Send a message": {
      "main": [
        [
          {
            "node": "Respond to Webhook",
            "type": "main",
            "index": 0
          }
        ]
      ]
    },
    "Imagen": {
      "main": [
        [
          {
            "node": "Send a message",
            "type": "main",
            "index": 0
          }
        ]
      ]
    },
    "Discord Webhook": {
      "main": [
        [
          {
            "node": "Imagen",
            "type": "main",
            "index": 0
          }
        ]
      ]
    },
    "Code in JavaScript1": {
      "main": [
        [
          {
            "node": "Send a message1",
            "type": "main",
            "index": 0
          }
        ]
      ]
    }
  },
  "active": false,
  "settings": {
    "executionOrder": "v1",
    "binaryMode": "separate",
    "availableInMCP": false
  },
  "versionId": "ef7b53c3-cf32-4231-ae71-d7851c26c579",
  "meta": {
    "templateCredsSetupCompleted": true,
    "instanceId": "45d3fe1300633f68f726d0817c055db4096d5f85a16cae803cb69190bd92377b"
  },
  "nodeGroups": [],
  "id": "Jz79f02WeJVM6Lei",
  "tags": []
}
